gew/ItemList.py
gew/__init__.py
gew/exchange.py
gew/items.json
gew-0.0.17.data/data/items.json
gew-0.0.17.dist-info/DESCRIPTION.rst
gew-0.0.17.dist-info/METADATA
gew-0.0.17.dist-info/RECORD
gew-0.0.17.dist-info/WHEEL
gew-0.0.17.dist-info/metadata.json
gew-0.0.17.dist-info/top_level.txt
