Metadata-Version: 2.0
Name: gew
Version: 0.0.17
Summary: Old School RuneScape Grand Exchange wrapper
Home-page: https://github.com/Blankpanda/GE_wrapper
Author: Caleb Ellis
Author-email: elliscaleb1998@gmail.com
License: MIT
Keywords: api development
Platform: UNKNOWN
Classifier: Development Status :: 3 - Alpha
Classifier: Intended Audience :: Developers
Classifier: Topic :: Software Development :: Build Tools
Classifier: License :: OSI Approved :: MIT License
Classifier: Programming Language :: Python :: 3
Classifier: Programming Language :: Python :: 3.2
Classifier: Programming Language :: Python :: 3.3
Classifier: Programming Language :: Python :: 3.4
Classifier: Programming Language :: Python :: 3.5
